pandas_optimum/__init__.py
pandas_optimum/pandas_optimum.py
pandas_optimum-0.0.6.dist-info/LICENSE
pandas_optimum-0.0.6.dist-info/METADATA
pandas_optimum-0.0.6.dist-info/WHEEL
pandas_optimum-0.0.6.dist-info/top_level.txt
pandas_optimum-0.0.6.dist-info/RECORD
