Metadata-Version: 2.1
Name: pandas-optimum
Version: 0.0.6
Summary: Optimised pandas, Best practices in-built
Home-page: https://github.com/irajankumar/pandas-optimum
Author: Rajan Kumar
Project-URL: Bug Tracker, https://github.com/irajankumar/pandas-optimum/issues
Classifier: Programming Language :: Python :: 3
Classifier: License :: OSI Approved :: BSD License
Classifier: Operating System :: OS Independent
Requires-Python: >=3.9
License-File: LICENSE
Requires-Dist: pandas (==2.0.0)
Requires-Dist: pyArrow (==12.0.0)
